ait_cli.py
ait_cli-1.0.2.dist-info/METADATA
ait_cli-1.0.2.dist-info/WHEEL
ait_cli-1.0.2.dist-info/entry_points.txt
ait_cli-1.0.2.dist-info/top_level.txt
ait_cli-1.0.2.dist-info/RECORD
