Metadata-Version: 2.4
Name: ait-cli
Version: 1.0.2
Summary: Command Line Tools for AIT
Author: AIST AIRC
License: Apache License Version 2.0
Keywords: ait,ait-sdk,ait-cli,qunomon,aist
Requires-Python: >=3.9
